py_cron_expression/__init__.py
py_cron_expression/py_cron.py
py_cron_expression/util.py
py_cron_expression/validations.py
tests/__init__.py
tests/test_cron_expression.py
tests/test_daily.py
tests/test_hourly.py
tests/test_minute.py
tests/test_validations.py
tests/test_weekly.py
PyCronExpression-1.0.1.dist-info/LICENSE
PyCronExpression-1.0.1.dist-info/METADATA
PyCronExpression-1.0.1.dist-info/WHEEL
PyCronExpression-1.0.1.dist-info/top_level.txt
PyCronExpression-1.0.1.dist-info/RECORD
