Metadata-Version: 2.1
Name: PyCronExpression
Version: 1.0.1
Summary: A simple Python Cron Expression lib
Home-page: https://github.com/vubon/PyCronExpression.git
Author: Vubon Roy
Author-email: vubon.roy@gmail.com
License: MIT
Classifier: Programming Language :: Python :: 3
Classifier: License :: OSI Approved :: MIT License
Classifier: Operating System :: OS Independent
Requires-Python: >=3.6
License-File: LICENSE
Requires-Dist: pytz
Requires-Dist: tzlocal
